gradio_rich_textbox/__init__.py
gradio_rich_textbox/richtextbox.py
gradio_rich_textbox/richtextbox.pyi
gradio_rich_textbox/templates/component/index.js
gradio_rich_textbox/templates/component/style.css
gradio_rich_textbox/templates/example/index.js
gradio_rich_textbox/templates/example/style.css
gradio_rich_textbox-0.4.3.dist-info/METADATA
gradio_rich_textbox-0.4.3.dist-info/WHEEL
gradio_rich_textbox-0.4.3.dist-info/RECORD
